temporalio/__init__.py
temporalio/activity.py
temporalio/api/__init__.py
temporalio/api/batch/__init__.py
temporalio/api/batch/v1/__init__.py
temporalio/api/batch/v1/message_pb2.py
temporalio/api/batch/v1/message_pb2.pyi
temporalio/api/cluster/__init__.py
temporalio/api/cluster/v1/__init__.py
temporalio/api/cluster/v1/message_pb2.py
temporalio/api/cluster/v1/message_pb2.pyi
temporalio/api/cluster/v1/message_pb2_grpc.py
temporalio/api/cluster/v1/message_pb2_grpc.pyi
temporalio/api/command/__init__.py
temporalio/api/command/v1/__init__.py
temporalio/api/command/v1/message_pb2.py
temporalio/api/command/v1/message_pb2.pyi
temporalio/api/common/__init__.py
temporalio/api/common/v1/__init__.py
temporalio/api/common/v1/grpc_status_pb2.py
temporalio/api/common/v1/grpc_status_pb2.pyi
temporalio/api/common/v1/message_pb2.py
temporalio/api/common/v1/message_pb2.pyi
temporalio/api/dependencies/__init__.py
temporalio/api/dependencies/gogoproto/__init__.py
temporalio/api/dependencies/gogoproto/gogo_pb2.py
temporalio/api/dependencies/gogoproto/gogo_pb2.pyi
temporalio/api/enums/__init__.py
temporalio/api/enums/v1/__init__.py
temporalio/api/enums/v1/batch_operation_pb2.py
temporalio/api/enums/v1/batch_operation_pb2.pyi
temporalio/api/enums/v1/command_type_pb2.py
temporalio/api/enums/v1/command_type_pb2.pyi
temporalio/api/enums/v1/common_pb2.py
temporalio/api/enums/v1/common_pb2.pyi
temporalio/api/enums/v1/event_type_pb2.py
temporalio/api/enums/v1/event_type_pb2.pyi
temporalio/api/enums/v1/failed_cause_pb2.py
temporalio/api/enums/v1/failed_cause_pb2.pyi
temporalio/api/enums/v1/interaction_type_pb2.py
temporalio/api/enums/v1/interaction_type_pb2.pyi
temporalio/api/enums/v1/namespace_pb2.py
temporalio/api/enums/v1/namespace_pb2.pyi
temporalio/api/enums/v1/query_pb2.py
temporalio/api/enums/v1/query_pb2.pyi
temporalio/api/enums/v1/reset_pb2.py
temporalio/api/enums/v1/reset_pb2.pyi
temporalio/api/enums/v1/schedule_pb2.py
temporalio/api/enums/v1/schedule_pb2.pyi
temporalio_arta-1.0.0.dist-info/WHEEL
temporalio_arta-1.0.0.dist-info/LICENSE
temporalio_arta-1.0.0.dist-info/METADATA
temporalio_arta-1.0.0.dist-info/RECORD
