Metadata-Version: 2.1
Name: temporalio-arta
Version: 1.0.0
Summary: Temporal.io Python SDK
Home-page: https://github.com/temporalio/sdk-python
License: MIT
Keywords: temporal,workflow
Author: Temporal Technologies Inc
Author-email: sdk@temporal.io
Requires-Python: >=3.7,<4.0
Classifier: License :: OSI Approved :: MIT License
Classifier: Programming Language :: Python :: 3
Classifier: Programming Language :: Python :: 3.7
Classifier: Programming Language :: Python :: 3.8
Classifier: Programming Language :: Python :: 3.9
Classifier: Programming Language :: Python :: 3.10
Classifier: Programming Language :: Python :: 3.11
Provides-Extra: grpc
Provides-Extra: opentelemetry
Requires-Dist: grpcio (>=1.48.0,<2.0.0) ; extra == "grpc"
Requires-Dist: opentelemetry-api (>=1.11.1,<2.0.0) ; extra == "opentelemetry"
Requires-Dist: opentelemetry-sdk (>=1.11.1,<2.0.0) ; extra == "opentelemetry"
Requires-Dist: protobuf (>=3.20)
Requires-Dist: python-dateutil (>=2.8.2,<3.0.0) ; python_version < "3.11"
Requires-Dist: types-protobuf (>=3.20,<3.21)
Requires-Dist: typing-extensions (>=4.2.0,<5.0.0)
Project-URL: Bug Tracker, https://github.com/temporalio/sdk-python/issues
Project-URL: Documentation, https://docs.temporal.io/docs/python
Project-URL: Repository, https://github.com/temporalio/sdk-python
